odoo/addons/budget_control_exception/README.rst
odoo/addons/budget_control_exception/__init__.py
odoo/addons/budget_control_exception/__manifest__.py
odoo/addons/budget_control_exception/data/budget_control_exception_data.xml
odoo/addons/budget_control_exception/models/__init__.py
odoo/addons/budget_control_exception/models/budget_control.py
odoo/addons/budget_control_exception/models/exception_rule.py
odoo/addons/budget_control_exception/readme/CONTRIBUTORS.md
odoo/addons/budget_control_exception/readme/DESCRIPTION.md
odoo/addons/budget_control_exception/security/ir.model.access.csv
odoo/addons/budget_control_exception/static/description/icon.png
odoo/addons/budget_control_exception/static/description/index.html
odoo/addons/budget_control_exception/tests/__init__.py
odoo/addons/budget_control_exception/tests/test_budget_control_exception.py
odoo/addons/budget_control_exception/views/budget_control_exception_view.xml
odoo/addons/budget_control_exception/wizard/__init__.py
odoo/addons/budget_control_exception/wizard/budget_control_exception_confirm.py
odoo/addons/budget_control_exception/wizard/budget_control_exception_confirm_view.xml
odoo_addon_budget_control_exception-18.0.1.0.0.1.dist-info/METADATA
odoo_addon_budget_control_exception-18.0.1.0.0.1.dist-info/WHEEL
odoo_addon_budget_control_exception-18.0.1.0.0.1.dist-info/top_level.txt
odoo_addon_budget_control_exception-18.0.1.0.0.1.dist-info/RECORD
